Day5_8bit_OddCounter/design.sv
// Code your design here
module odd_counter(
  input clk,
  input reset,
  output  reg[7:0] cnt);
  
  logic [7:0] nxt_cnt;
  
  always@(posedge clk or posedge reset)
    if(reset)
      cnt <=0;
  else
    cnt <= nxt_cnt;
  
  assign nxt_cnt = cnt + 8'h2;
  
endmodule

Day5_8bit_OddCounter/testbench.sv
// Code your testbench here
// or browse Examples
module odd_tb();
  logic clk;
  logic reset;
  logic [7:0] cnt;
  
  odd_counter oc(.*);
    
  always begin
    clk = 1'b0;
    #5;
    clk = 1'b1;
    #5;
  end
  
   initial begin
    reset <= 1'b1;
    @(posedge clk);
    @(posedge clk);
    reset <= 1'b0;
    for (int i=0; i<128; i++)
      @(posedge clk);
    $finish();
  end

  initial begin
    $dumpfile("day5.vcd");
    $dumpvars(0, odd_tb);
  end
  
endmodule

Day5_8bit_OddCounter/day5.vcd
$date
	Thu Nov  3 12:05:58 2022
$end
$version
	Icarus Verilog
$end
$timescale
	1s
$end
$scope module odd_tb $end
$var wire 8 ! cnt [7:0] $end
$var reg 1 " clk $end
$var reg 1 # reset $end
$scope module oc $end
$var wire 1 " clk $end
$var wire 1 # reset $end
$var wire 8 $ nxt_cnt [7:0] $end
$var reg 8 % cnt [7:0] $end
$upscope $end
$scope begin $ivl_for_loop0 $end
$var integer 32 & i [31:0] $end
$upscope $end
$upscope $end
$enddefinitions $end
#0
$dumpvars
b0 &
b0 %
b10 $
1#
0"
b0 !
$end
#5
1"
#10
0"
#15
0#
1"
#20
0"
#25
b100 $
b10 !
b10 %
b1 &
1"
#30
0"
#35
b110 $
b100 !
b100 %
b10 &
1"
#40
0"
#45
b1000 $
b110 !
b110 %
b11 &
1"
#50
0"
#55
b1010 $
b1000 !
b1000 %
b100 &
1"
#60
0"
#65
b1100 $
b1010 !
b1010 %
b101 &
1"
#70
0"
#75
b1110 $
b1100 !
b1100 %
b110 &
1"
#80
0"
#85
b10000 $
b1110 !
b1110 %
b111 &
1"
#90
0"
#95
b10010 $
b10000 !
b10000 %
b1000 &
1"
#100
0"
#105
b10100 $
b10010 !
b10010 %
b1001 &
1"
#110
0"
#115
b10110 $
b10100 !
b10100 %
b1010 &
1"
#120
0"
#125
b11000 $
b10110 !
b10110 %
b1011 &
1"
#130
0"
#135
b11010 $
b11000 !
b11000 %
b1100 &
1"
#140
0"
#145
b11100 $
b11010 !
b11010 %
b1101 &
1"
#150
0"
#155
b11110 $
b11100 !
b11100 %
b1110 &
1"
#160
0"
#165
b100000 $
b11110 !
b11110 %
b1111 &
1"
#170
0"
#175
b100010 $
b100000 !
b100000 %
b10000 &
1"
#180
0"
#185
b100100 $
b100010 !
b100010 %
b10001 &
1"
#190
0"
#195
b100110 $
b100100 !
b100100 %
b10010 &
1"
#200
0"
#205
b101000 $
b100110 !
b100110 %
b10011 &
1"
#210
0"
#215
b101010 $
b101000 !
b101000 %
b10100 &
1"
#220
0"
#225
b101100 $
b101010 !
b101010 %
b10101 &
1"
#230
0"
#235
b101110 $
b101100 !
b101100 %
b10110 &
1"
#240
0"
#245
b110000 $
b101110 !
b101110 %
b10111 &
1"
#250
0"
#255
b110010 $
b110000 !
b110000 %
b11000 &
1"
#260
0"
#265
b110100 $
b110010 !
b110010 %
b11001 &
1"
#270
0"
#275
b110110 $
b110100 !
b110100 %
b11010 &
1"
#280
0"
#285
b111000 $
b110110 !
b110110 %
b11011 &
1"
#290
0"
#295
b111010 $
b111000 !
b111000 %
b11100 &
1"
#300
0"
#305
b111100 $
b111010 !
b111010 %
b11101 &
1"
#310
0"
#315
b111110 $
b111100 !
b111100 %
b11110 &
1"
#320
0"
#325
b1000000 $
b111110 !
b111110 %
b11111 &
1"
#330
0"
#335
b1000010 $
b1000000 !
b1000000 %
b100000 &
1"
#340
0"
#345
b1000100 $
b1000010 !
b1000010 %
b100001 &
1"
#350
0"
#355
b1000110 $
b1000100 !
b1000100 %
b100010 &
1"
#360
0"
#365
b1001000 $
b1000110 !
b1000110 %
b100011 &
1"
#370
0"
#375
b1001010 $
b1001000 !
b1001000 %
b100100 &
1"
#380
0"
#385
b1001100 $
b1001010 !
b1001010 %
b100101 &
1"
#390
0"
#395
b1001110 $
b1001100 !
b1001100 %
b100110 &
1"
#400
0"
#405
b1010000 $
b1001110 !
b1001110 %
b100111 &
1"
#410
0"
#415
b1010010 $
b1010000 !
b1010000 %
b101000 &
1"
#420
0"
#425
b1010100 $
b1010010 !
b1010010 %
b101001 &
1"
#430
0"
#435
b1010110 $
b1010100 !
b1010100 %
b101010 &
1"
#440
0"
#445
b1011000 $
b1010110 !
b1010110 %
b101011 &
1"
#450
0"
#455
b1011010 $
b1011000 !
b1011000 %
b101100 &
1"
#460
0"
#465
b1011100 $
b1011010 !
b1011010 %
b101101 &
1"
#470
0"
#475
b1011110 $
b1011100 !
b1011100 %
b101110 &
1"
#480
0"
#485
b1100000 $
b1011110 !
b1011110 %
b101111 &
1"
#490
0"
#495
b1100010 $
b1100000 !
b1100000 %
b110000 &
1"
#500
0"
#505
b1100100 $
b1100010 !
b1100010 %
b110001 &
1"
#510
0"
#515
b1100110 $
b1100100 !
b1100100 %
b110010 &
1"
#520
0"
#525
b1101000 $
b1100110 !
b1100110 %
b110011 &
1"
#530
0"
#535
b1101010 $
b1101000 !
b1101000 %
b110100 &
1"
#540
0"
#545
b1101100 $
b1101010 !
b1101010 %
b110101 &
1"
#550
0"
#555
b1101110 $
b1101100 !
b1101100 %
b110110 &
1"
#560
0"
#565
b1110000 $
b1101110 !
b1101110 %
b110111 &
1"
#570
0"
#575
b1110010 $
b1110000 !
b1110000 %
b111000 &
1"
#580
0"
#585
b1110100 $
b1110010 !
b1110010 %
b111001 &
1"
#590
0"
#595
b1110110 $
b1110100 !
b1110100 %
b111010 &
1"
#600
0"
#605
b1111000 $
b1110110 !
b1110110 %
b111011 &
1"
#610
0"
#615
b1111010 $
b1111000 !
b1111000 %
b111100 &
1"
#620
0"
#625
b1111100 $
b1111010 !
b1111010 %
b111101 &
1"
#630
0"
#635
b1111110 $
b1111100 !
b1111100 %
b111110 &
1"
#640
0"
#645
b10000000 $
b1111110 !
b1111110 %
b111111 &
1"
#650
0"
#655
b10000010 $
b10000000 !
b10000000 %
b1000000 &
1"
#660
0"
#665
b10000100 $
b10000010 !
b10000010 %
b1000001 &
1"
#670
0"
#675
b10000110 $
b10000100 !
b10000100 %
b1000010 &
1"
#680
0"
#685
b10001000 $
b10000110 !
b10000110 %
b1000011 &
1"
#690
0"
#695
b10001010 $
b10001000 !
b10001000 %
b1000100 &
1"
#700
0"
#705
b10001100 $
b10001010 !
b10001010 %
b1000101 &
1"
#710
0"
#715
b10001110 $
b10001100 !
b10001100 %
b1000110 &
1"
#720
0"
#725
b10010000 $
b10001110 !
b10001110 %
b1000111 &
1"
#730
0"
#735
b10010010 $
b10010000 !
b10010000 %
b1001000 &
1"
#740
0"
#745
b10010100 $
b10010010 !
b10010010 %
b1001001 &
1"
#750
0"
#755
b10010110 $
b10010100 !
b10010100 %
b1001010 &
1"
#760
0"
#765
b10011000 $
b10010110 !
b10010110 %
b1001011 &
1"
#770
0"
#775
b10011010 $
b10011000 !
b10011000 %
b1001100 &
1"
#780
0"
#785
b10011100 $
b10011010 !
b10011010 %
b1001101 &
1"
#790
0"
#795
b10011110 $
b10011100 !
b10011100 %
b1001110 &
1"
#800
0"
#805
b10100000 $
b10011110 !
b10011110 %
b1001111 &
1"
#810
0"
#815
b10100010 $
b10100000 !
b10100000 %
b1010000 &
1"
#820
0"
#825
b10100100 $
b10100010 !
b10100010 %
b1010001 &
1"
#830
0"
#835
b10100110 $
b10100100 !
b10100100 %
b1010010 &
1"
#840
0"
#845
b10101000 $
b10100110 !
b10100110 %
b1010011 &
1"
#850
0"
#855
b10101010 $
b10101000 !
b10101000 %
b1010100 &
1"
#860
0"
#865
b10101100 $
b10101010 !
b10101010 %
b1010101 &
1"
#870
0"
#875
b10101110 $
b10101100 !
b10101100 %
b1010110 &
1"
#880
0"
#885
b10110000 $
b10101110 !
b10101110 %
b1010111 &
1"
#890
0"
#895
b10110010 $
b10110000 !
b10110000 %
b1011000 &
1"
#900
0"
#905
b10110100 $
b10110010 !
b10110010 %
b1011001 &
1"
#910
0"
#915
b10110110 $
b10110100 !
b10110100 %
b1011010 &
1"
#920
0"
#925
b10111000 $
b10110110 !
b10110110 %
b1011011 &
1"
#930
0"
#935
b10111010 $
b10111000 !
b10111000 %
b1011100 &
1"
#940
0"
#945
b10111100 $
b10111010 !
b10111010 %
b1011101 &
1"
#950
0"
#955
b10111110 $
b10111100 !
b10111100 %
b1011110 &
1"
#960
0"
#965
b11000000 $
b10111110 !
b10111110 %
b1011111 &
1"
#970
0"
#975
b11000010 $
b11000000 !
b11000000 %
b1100000 &
1"
#980
0"
#985
b11000100 $
b11000010 !
b11000010 %
b1100001 &
1"
#990
0"
#995
b11000110 $
b11000100 !
b11000100 %
b1100010 &
1"
#1000
0"
#1005
b11001000 $
b11000110 !
b11000110 %
b1100011 &
1"
#1010
0"
#1015
b11001010 $
b11001000 !
b11001000 %
b1100100 &
1"
#1020
0"
#1025
b11001100 $
b11001010 !
b11001010 %
b1100101 &
1"
#1030
0"
#1035
b11001110 $
b11001100 !
b11001100 %
b1100110 &
1"
#1040
0"
#1045
b11010000 $
b11001110 !
b11001110 %
b1100111 &
1"
#1050
0"
#1055
b11010010 $
b11010000 !
b11010000 %
b1101000 &
1"
#1060
0"
#1065
b11010100 $
b11010010 !
b11010010 %
b1101001 &
1"
#1070
0"
#1075
b11010110 $
b11010100 !
b11010100 %
b1101010 &
1"
#1080
0"
#1085
b11011000 $
b11010110 !
b11010110 %
b1101011 &
1"
#1090
0"
#1095
b11011010 $
b11011000 !
b11011000 %
b1101100 &
1"
#1100
0"
#1105
b11011100 $
b11011010 !
b11011010 %
b1101101 &
1"
#1110
0"
#1115
b11011110 $
b11011100 !
b11011100 %
b1101110 &
1"
#1120
0"
#1125
b11100000 $
b11011110 !
b11011110 %
b1101111 &
1"
#1130
0"
#1135
b11100010 $
b11100000 !
b11100000 %
b1110000 &
1"
#1140
0"
#1145
b11100100 $
b11100010 !
b11100010 %
b1110001 &
1"
#1150
0"
#1155
b11100110 $
b11100100 !
b11100100 %
b1110010 &
1"
#1160
0"
#1165
b11101000 $
b11100110 !
b11100110 %
b1110011 &
1"
#1170
0"
#1175
b11101010 $
b11101000 !
b11101000 %
b1110100 &
1"
#1180
0"
#1185
b11101100 $
b11101010 !
b11101010 %
b1110101 &
1"
#1190
0"
#1195
b11101110 $
b11101100 !
b11101100 %
b1110110 &
1"
#1200
0"
#1205
b11110000 $
b11101110 !
b11101110 %
b1110111 &
1"
#1210
0"
#1215
b11110010 $
b11110000 !
b11110000 %
b1111000 &
1"
#1220
0"
#1225
b11110100 $
b11110010 !
b11110010 %
b1111001 &
1"
#1230
0"
#1235
b11110110 $
b11110100 !
b11110100 %
b1111010 &
1"
#1240
0"
#1245
b11111000 $
b11110110 !
b11110110 %
b1111011 &
1"
#1250
0"
#1255
b11111010 $
b11111000 !
b11111000 %
b1111100 &
1"
#1260
0"
#1265
b11111100 $
b11111010 !
b11111010 %
b1111101 &
1"
#1270
0"
#1275
b11111110 $
b11111100 !
b11111100 %
b1111110 &
1"
#1280
0"
#1285
b0 $
b11111110 !
b11111110 %
b1111111 &
1"
#1290
0"
#1295
b10 $
b0 !
b0 %
b10000000 &
1"
