Day13_Mux_Multiple_implementations/design.sv
// Code your design here
// Various ways to implement a mux

module mux (
  input     logic[3:0] a_i,
  input     logic[3:0] sel_i,

  // Output using ternary operator
  output   logic     y_ter_o,
  // Output using case
  output   logic     y_case_o,
  // Ouput using if-else
  output   logic     y_ifelse_o,
  // Output using for loop
  output   logic    y_loop_o,
  // Output using and-or tree
  output    logic    y_aor_o
);

  // Ternary operator
  assign y_ter_o = sel_i[0] ? a_i[0] :
                   sel_i[1] ? a_i[1] :
                   sel_i[2] ? a_i[2] :
                              a_i[3];

  // Using case
  always@(*) begin
    case (sel_i)
      4'b0001 : y_case_o = a_i[0];
      4'b0010 : y_case_o = a_i[1];
      4'b0100 : y_case_o = a_i[2];
      4'b1000 : y_case_o = a_i[3];
      default : y_case_o = 1'bx;
    endcase
  end

  // Using ifelse
  always@(*) begin
    if (sel_i[0])      y_ifelse_o = a_i[0];
    else if (sel_i[1]) y_ifelse_o = a_i[1];
    else if (sel_i[2]) y_ifelse_o = a_i[2];
    else if (sel_i[3]) y_ifelse_o = a_i[3];
    else               y_ifelse_o = 1'bx;
  end

  // Using for loop
  always@(*) begin
    y_loop_o = '0;
    for (int i=0; i<4; i++) begin
      y_loop_o = (sel_i[i] & a_i[i]) | y_loop_o;
    end
  end

  // Using and-or tree
  assign y_aor_o = (sel_i[0] & a_i[0]) |
                   (sel_i[1] & a_i[1]) |
                   (sel_i[2] & a_i[2]) |
                   (sel_i[3] & a_i[3]);

endmodule

Day13_Mux_Multiple_implementations/testbench.sv
// Code your testbench here
// or browse Examples
// Simple TB

module mux_tb ();

  
  logic [3:0] a_i;
  logic [3:0] sel_i;

  // Output using ternary operator
  logic     y_ter_o;
  // Output using case
  logic     y_case_o;
  // Ouput using if-else
  logic     y_ifelse_o;
  // Output using for loop
  logic     y_loop_o;
  // Output using and-or tree
  logic     y_aor_o;

  // Module instance
  mux DAY13 (.*);

  // Stimulus
  initial begin
    for (int i =0; i<32; i++) begin
      a_i   = $urandom_range(0, 4'hF);
      sel_i = 1'b1 << $urandom_range(0, 2'h3); // one-hot
      #5;
    end
    $finish();
  end

  // VCD
  initial begin
    $dumpfile("day13.vcd");
    $dumpvars(0, mux_tb);
  end

endmodule

Day13_Mux_Multiple_implementations/day13.vcd
$date
	Tue Jan 10 21:28:41 2023
$end
$version
	Icarus Verilog
$end
$timescale
	1s
$end
$scope module mux_tb $end
$var wire 1 ! y_ter_o $end
$var wire 1 " y_loop_o $end
$var wire 1 # y_ifelse_o $end
$var wire 1 $ y_case_o $end
$var wire 1 % y_aor_o $end
$var reg 4 & a_i [3:0] $end
$var reg 4 ' sel_i [3:0] $end
$scope module DAY13 $end
$var wire 4 ( a_i [3:0] $end
$var wire 4 ) sel_i [3:0] $end
$var wire 1 % y_aor_o $end
$var wire 1 ! y_ter_o $end
$var reg 1 $ y_case_o $end
$var reg 1 # y_ifelse_o $end
$var reg 1 " y_loop_o $end
$scope begin $ivl_for_loop0 $end
$var integer 32 * i [31:0] $end
$upscope $end
$upscope $end
$scope begin $ivl_for_loop1 $end
$var integer 32 + i [31:0] $end
$upscope $end
$upscope $end
$enddefinitions $end
#0
$dumpvars
b0 +
b100 *
b10 )
b1001 (
b10 '
b1001 &
0%
0$
0#
0"
0!
$end
#5
b100 *
b1 '
b1 )
b0 &
b0 (
b1 +
#10
1!
1%
1"
b100 *
1#
1$
b1000 '
b1000 )
b1000 &
b1000 (
b10 +
#15
1%
b100 *
1"
b1 '
b1 )
b11 &
b11 (
b11 +
#20
0%
0!
b100 *
0"
0#
0$
b100 '
b100 )
b1000 &
b1000 (
b100 +
#25
b100 *
b1011 &
b1011 (
b101 +
#30
1!
1%
1"
b100 *
1#
1$
b1000 '
b1000 )
b1111 &
b1111 (
b110 +
#35
1%
b100 *
1"
b10 '
b10 )
b111 +
#40
b100 *
1"
b110 &
b110 (
b1000 +
#45
b100 *
1"
b1 '
b1 )
b1111 &
b1111 (
b1001 +
#50
0%
0!
b100 *
0"
0#
0$
b1000 '
b1000 )
b0 &
b0 (
b1010 +
#55
1%
1!
1"
b100 *
1$
1#
b10 '
b10 )
b1111 &
b1111 (
b1011 +
#60
b100 *
1"
b111 &
b111 (
b1100 +
#65
b100 *
1"
b1010 &
b1010 (
b1101 +
#70
b100 *
1"
b1 '
b1 )
b1 &
b1 (
b1110 +
#75
0%
0!
b100 *
0"
0$
0#
b100 '
b100 )
b11 &
b11 (
b1111 +
#80
1!
1%
1"
b100 *
1#
1$
b100 &
b100 (
b10000 +
#85
0%
0!
b100 *
0"
0$
0#
b10 '
b10 )
b1101 &
b1101 (
b10001 +
#90
b100 *
b1 '
b1 )
b100 &
b100 (
b10010 +
#95
b100 *
b0 &
b0 (
b10011 +
#100
1%
1!
1"
b100 *
1#
1$
b10 '
b10 )
b1011 &
b1011 (
b10100 +
#105
0%
0!
b100 *
0"
0$
0#
b0 &
b0 (
b10101 +
#110
b100 *
b1000 &
b1000 (
b10110 +
#115
b100 *
b100 '
b100 )
b1001 &
b1001 (
b10111 +
#120
b100 *
b1 '
b1 )
b110 &
b110 (
b11000 +
#125
1!
1%
1"
b100 *
1$
1#
b1000 '
b1000 )
b1111 &
b1111 (
b11001 +
#130
1%
b100 *
1"
b10 '
b10 )
b1010 &
b1010 (
b11010 +
#135
b100 *
1"
b1011 &
b1011 (
b11011 +
#140
b100 *
1"
b1000 '
b1000 )
b1111 &
b1111 (
b11100 +
#145
b100 *
1"
b1110 &
b1110 (
b11101 +
#150
1%
b100 *
1"
b100 '
b100 )
b101 &
b101 (
b11110 +
#155
0%
0!
b100 *
0"
0$
0#
b1 '
b1 )
b0 &
b0 (
b11111 +
#160
b100000 +
