Day4_ALU/design.sv
// Code your design here
module ALU(
  input [7:0] a,
  input [7:0] b,
  input [2:0] op,
  output  reg [7:0] alu_o
);
  
  //Enum for ALU
  
   // Enum for ALU op
  localparam  OP_ADD = 3'b000;
  localparam  OP_SUB = 3'b001;
  localparam  OP_SLL = 3'b010;
  localparam  OP_LSR = 3'b011;
  localparam  OP_AND = 3'b100;
  localparam  OP_OR  = 3'b101;
  localparam  OP_XOR = 3'b110;
  localparam  OP_EQL = 3'b111;

  reg carry;
  
  always @(*)
  begin
    case(op)
      OP_ADD: {carry,alu_o} = a+b;
      OP_SUB: alu_o = a-b;
      OP_SLL: alu_o = a << b; 
      OP_LSR: alu_o = a >> b;
      OP_AND: alu_o = a & b;
      OP_OR:  alu_o = a | b;
      OP_XOR: alu_o = a ^ b;
      OP_EQL: alu_o = {7'h0, a == b};  
    endcase
  end
  
endmodule

Day4_ALU/testbench.sv
// Code your testbench here
// or browse Examples
module ALU_Tb();
  reg [7:0] a,b;
  reg [2:0] op;
  wire [7:0] alu_o;
  integer i,j;
  
  ALU alu (.a(a),.b(b),.op(op),.alu_o(alu_o));
  
  initial
    begin
      for(j=0;j<3;j=j+1)
        begin
        for(i=0;i<7;i=i+1)
          begin
          a = $urandom_range(0,8'hFF);
          b = $urandom_range(0,8'hFF);
          op = i;
          #5;
    	end
  	end
  end
  
  initial begin
    $dumpfile("day4.vcd");
    $dumpvars(0, ALU_Tb);
  end
endmodule

Day4_ALU/day4.vcd
$date
	Thu Nov  3 11:47:10 2022
$end
$version
	Icarus Verilog
$end
$timescale
	1s
$end
$scope module ALU_Tb $end
$var wire 8 ! alu_o [7:0] $end
$var reg 8 " a [7:0] $end
$var reg 8 # b [7:0] $end
$var reg 3 $ op [2:0] $end
$var integer 32 % i [31:0] $end
$var integer 32 & j [31:0] $end
$scope module alu $end
$var wire 8 ' a [7:0] $end
$var wire 8 ( b [7:0] $end
$var wire 3 ) op [2:0] $end
$var reg 8 * alu_o [7:0] $end
$var reg 1 + carry $end
$upscope $end
$upscope $end
$enddefinitions $end
#0
$dumpvars
0+
b11010010 *
b0 )
b1000000 (
b10010010 '
b0 &
b0 %
b0 $
b1000000 #
b10010010 "
b11010010 !
$end
#5
b11010011 !
b11010011 *
b1 $
b1 )
b110001 #
b110001 (
b100 "
b100 '
b1 %
#10
b0 !
b0 *
b10 $
b10 )
b11000110 #
b11000110 (
b10000110 "
b10000110 '
b10 %
#15
b11 $
b11 )
b1001 #
b1001 (
b110010 "
b110010 '
b11 %
#20
b10000000 !
b10000000 *
b100 $
b100 )
b10000110 #
b10000110 (
b10000000 "
b10000000 '
b100 %
#25
b10111111 !
b10111111 *
b101 $
b101 )
b10011110 #
b10011110 (
b10111011 "
b10111011 '
b101 %
#30
b110000 !
b110000 *
b110 $
b110 )
b11000110 #
b11000110 (
b11110110 "
b11110110 '
b110 %
#35
1+
b1011111 !
b1011111 *
b0 $
b0 )
b1100011 #
b1100011 (
b11111100 "
b11111100 '
b1 &
b0 %
#40
b1101 !
b1101 *
b1 $
b1 )
b1010101 #
b1010101 (
b1100010 "
b1100010 '
b1 %
#45
b0 !
b0 *
b10 $
b10 )
b111011 #
b111011 (
b11110010 "
b11110010 '
b10 %
#50
b11 $
b11 )
b11000111 #
b11000111 (
b1001 "
b1001 '
b11 %
#55
b1100001 !
b1100001 *
b100 $
b100 )
b1100111 #
b1100111 (
b11111001 "
b11111001 '
b100 %
#60
b1110110 !
b1110110 *
b101 $
b101 )
b1100010 #
b1100010 (
b1110100 "
b1110100 '
b101 %
#65
b11110000 !
b11110000 *
b110 $
b110 )
b1011110 #
b1011110 (
b10101110 "
b10101110 '
b110 %
#70
0+
b1001000 !
b1001000 *
b0 $
b0 )
b110010 #
b110010 (
b10110 "
b10110 '
b10 &
b0 %
#75
b10101100 !
b10101100 *
b1 $
b1 )
b10000101 #
b10000101 (
b110001 "
b110001 '
b1 %
#80
b0 !
b0 *
b10 $
b10 )
b10010000 #
b10010000 (
b1000000 "
b1000000 '
b10 %
#85
b11 $
b11 )
b1001110 #
b1001110 (
b11010101 "
b11010101 '
b11 %
#90
b1001 !
b1001 *
b100 $
b100 )
b1001 #
b1001 (
b1001011 "
b1001011 '
b100 %
#95
b101111 !
b101111 *
b101 $
b101 )
b101001 #
b101001 (
b110 "
b110 '
b101 %
#100
b11011111 !
b11011111 *
b110 $
b110 )
b1101010 #
b1101010 (
b10110101 "
b10110101 '
b110 %
#105
b11 &
b111 %
