Day8_binary_Onehot/design.sv
module BtoO#(
  parameter BIN_W       = 4,
  parameter ONE_HOT_W   = 16
)(
  input   wire[BIN_W-1:0]     bin_i,
  output  wire[ONE_HOT_W-1:0] one_hot_o
);

  assign one_hot_o = 1'b1<<bin_i;

endmodule

Day8_binary_Onehot/testbench.sv
// Code your testbench here
// or browse Examples
module b2o_tb();

  localparam BIN_W = 4;
  localparam ONE_HOT_W = 16;

  logic [BIN_W-1:0] bin_i;
  logic [ONE_HOT_W-1:0] one_hot_o;

  BtoO #(BIN_W, ONE_HOT_W) b2o (.*);

  initial begin
    for(int i=0; i<32; i=i+1) begin
      bin_i = $urandom_range(0, 4'hF);
      #5;
    end
    $finish();
  end

  initial begin
    $dumpfile("day8.vcd");
    $dumpvars(2, b2o_tb);
  end

endmodule

Day8_binary_Onehot/day8.vcd
$date
	Sat Nov 12 23:26:00 2022
$end
$version
	Icarus Verilog
$end
$timescale
	1s
$end
$scope module b2o_tb $end
$var wire 16 ! one_hot_o [15:0] $end
$var reg 4 " bin_i [3:0] $end
$scope module b2o $end
$var wire 4 # bin_i [3:0] $end
$var wire 16 $ one_hot_o [15:0] $end
$upscope $end
$scope begin $ivl_for_loop0 $end
$var integer 32 % i [31:0] $end
$upscope $end
$upscope $end
$enddefinitions $end
#0
$dumpvars
b0 %
b1000000000 $
b1001 #
b1001 "
b1000000000 !
$end
#5
b10000 !
b10000 $
b100 "
b100 #
b1 %
#10
b1 !
b1 $
b0 "
b0 #
b10 %
#15
b1000 !
b1000 $
b11 "
b11 #
b11 %
#20
b100000000 !
b100000000 $
b1000 "
b1000 #
b100 %
#25
b1000000000000 !
b1000000000000 $
b1100 "
b1100 #
b101 %
#30
b1000 !
b1000 $
b11 "
b11 #
b110 %
#35
b1 !
b1 $
b0 "
b0 #
b111 %
#40
b100000000 !
b100000000 $
b1000 "
b1000 #
b1000 %
#45
b1001 %
#50
b100000000000 !
b100000000000 $
b1011 "
b1011 #
b1010 %
#55
b1000000000 !
b1000000000 $
b1001 "
b1001 #
b1011 %
#60
b1000000000000000 !
b1000000000000000 $
b1111 "
b1111 #
b1100 %
#65
b1000000000000 !
b1000000000000 $
b1100 "
b1100 #
b1101 %
#70
b1000000000000000 !
b1000000000000000 $
b1111 "
b1111 #
b1110 %
#75
b1000000 !
b1000000 $
b110 "
b110 #
b1111 %
#80
b10000 %
#85
b100000 !
b100000 $
b101 "
b101 #
b10001 %
#90
b1000000000000000 !
b1000000000000000 $
b1111 "
b1111 #
b10010 %
#95
b1000 !
b1000 $
b11 "
b11 #
b10011 %
#100
b1 !
b1 $
b0 "
b0 #
b10100 %
#105
b1000000000000 !
b1000000000000 $
b1100 "
b1100 #
b10101 %
#110
b1000000000000000 !
b1000000000000000 $
b1111 "
b1111 #
b10110 %
#115
b1000000 !
b1000000 $
b110 "
b110 #
b10111 %
#120
b10000000 !
b10000000 $
b111 "
b111 #
b11000 %
#125
b1000000 !
b1000000 $
b110 "
b110 #
b11001 %
#130
b10000000000 !
b10000000000 $
b1010 "
b1010 #
b11010 %
#135
b100000 !
b100000 $
b101 "
b101 #
b11011 %
#140
b10 !
b10 $
b1 "
b1 #
b11100 %
#145
b1000 !
b1000 $
b11 "
b11 #
b11101 %
#150
b11110 %
#155
b100000000 !
b100000000 $
b1000 "
b1000 #
b11111 %
#160
b100000 %
