Day7_4bit_linearFdbck/design.sv
// Code your design here
module xorsf(
  input wire clk,
  input wire reset,
  output wire[3:0] out);
  
  logic[3:0] present;
  logic[3:0] next;
  
  always@(posedge clk or posedge reset)
    begin
    if(reset)
      present <= 4'hE;
    else
      present <= next;
    end
  assign next = {present[2:0],present[1] ^ present[3]};
  assign out = present;
  
endmodule

Day7_4bit_linearFdbck/testbench.sv
// Code your testbench here
// or browse Examples
module sftb();
  logic clk;
  logic reset;
  logic[3:0] out;
  
  xorsf x1(.*);
  
 //Clock Generation 
  always
    begin
      clk = 1'b1;
      #5;
      clk = 1'b0;
      #5;
    end
  
  //Stimulus Generation
  
 initial 
   begin
     reset <=1'b1;
     @(posedge clk);
     reset <=1'b0;
     for(int i=0;i<32;i=i+1)
       @(posedge clk);
     $finish();
   end
  
   initial 
    begin
    $dumpfile("day7.vcd");
      $dumpvars(0, sftb);
  	end

endmodule

Day7_4bit_linearFdbck/day7.vcd
$date
	Tue Nov  8 20:01:37 2022
$end
$version
	Icarus Verilog
$end
$timescale
	1s
$end
$scope module sftb $end
$var wire 4 ! out [3:0] $end
$var reg 1 " clk $end
$var reg 1 # reset $end
$scope module x1 $end
$var wire 1 " clk $end
$var wire 4 $ out [3:0] $end
$var wire 1 # reset $end
$var wire 4 % next [3:0] $end
$var reg 4 & present [3:0] $end
$upscope $end
$scope begin $ivl_for_loop0 $end
$var integer 32 ' i [31:0] $end
$upscope $end
$upscope $end
$enddefinitions $end
#0
$dumpvars
b0 '
b1110 &
b1100 %
b1110 $
1#
1"
b1110 !
$end
#5
0"
#10
0#
1"
#15
0"
#20
b1001 %
b1100 !
b1100 $
b1100 &
b1 '
1"
#25
0"
#30
b11 %
b1001 !
b1001 $
b1001 &
b10 '
1"
#35
0"
#40
b111 %
b11 !
b11 $
b11 &
b11 '
1"
#45
0"
#50
b1111 %
b111 !
b111 $
b111 &
b100 '
1"
#55
0"
#60
b1110 %
b1111 !
b1111 $
b1111 &
b101 '
1"
#65
0"
#70
b1100 %
b1110 !
b1110 $
b1110 &
b110 '
1"
#75
0"
#80
b1001 %
b1100 !
b1100 $
b1100 &
b111 '
1"
#85
0"
#90
b11 %
b1001 !
b1001 $
b1001 &
b1000 '
1"
#95
0"
#100
b111 %
b11 !
b11 $
b11 &
b1001 '
1"
#105
0"
#110
b1111 %
b111 !
b111 $
b111 &
b1010 '
1"
#115
0"
#120
b1110 %
b1111 !
b1111 $
b1111 &
b1011 '
1"
#125
0"
#130
b1100 %
b1110 !
b1110 $
b1110 &
b1100 '
1"
#135
0"
#140
b1001 %
b1100 !
b1100 $
b1100 &
b1101 '
1"
#145
0"
#150
b11 %
b1001 !
b1001 $
b1001 &
b1110 '
1"
#155
0"
#160
b111 %
b11 !
b11 $
b11 &
b1111 '
1"
#165
0"
#170
b1111 %
b111 !
b111 $
b111 &
b10000 '
1"
#175
0"
#180
b1110 %
b1111 !
b1111 $
b1111 &
b10001 '
1"
#185
0"
#190
b1100 %
b1110 !
b1110 $
b1110 &
b10010 '
1"
#195
0"
#200
b1001 %
b1100 !
b1100 $
b1100 &
b10011 '
1"
#205
0"
#210
b11 %
b1001 !
b1001 $
b1001 &
b10100 '
1"
#215
0"
#220
b111 %
b11 !
b11 $
b11 &
b10101 '
1"
#225
0"
#230
b1111 %
b111 !
b111 $
b111 &
b10110 '
1"
#235
0"
#240
b1110 %
b1111 !
b1111 $
b1111 &
b10111 '
1"
#245
0"
#250
b1100 %
b1110 !
b1110 $
b1110 &
b11000 '
1"
#255
0"
#260
b1001 %
b1100 !
b1100 $
b1100 &
b11001 '
1"
#265
0"
#270
b11 %
b1001 !
b1001 $
b1001 &
b11010 '
1"
#275
0"
#280
b111 %
b11 !
b11 $
b11 &
b11011 '
1"
#285
0"
#290
b1111 %
b111 !
b111 $
b111 &
b11100 '
1"
#295
0"
#300
b1110 %
b1111 !
b1111 $
b1111 &
b11101 '
1"
#305
0"
#310
b1100 %
b1110 !
b1110 $
b1110 &
b11110 '
1"
#315
0"
#320
b1001 %
b1100 !
b1100 $
b1100 &
b11111 '
1"
#325
0"
#330
b11 %
b1001 !
b1001 $
b1001 &
b100000 '
1"
