Day9_Binary_to_Gray/design.sv

// Day-9 Binary to Gray Convertor

module BtoG
  ( input [3:0] Bini,
   output reg[3:0] Grayo
  );
  parameter length = 4;
  assign Grayo[3] = Bini[3];
  
  genvar i;
  for(i= length-2;i>=0;i=i-1)
    assign Grayo[i] = Bini[i+1] ^ Bini[i];
  
endmodule

Day9_Binary_to_Gray/testbench.sv
//Day-9
//Binary to Gray Convertor Test Bench

module gtob_tb();
  
  logic[3:0] Bini;
  logic[3:0] Grayo;
  
  BtoG btog(.*);
  
  initial
    begin
      for(int i=0;i<2**4;i=i+1)
        begin
        Bini = i;
        #5;
        end
      $finish();
    end
  
  initial
    begin
      $dumpfile("day9.vcd");
      $dumpvars(2,gtob_tb);    
    end            
                
 endmodule

Day9_Binary_to_Gray/day9.vcd
$date
	Tue Nov 15 02:36:57 2022
$end
$version
	Icarus Verilog
$end
$timescale
	1s
$end
$scope module gtob_tb $end
$var wire 4 ! Grayo [3:0] $end
$var reg 4 " Bini [3:0] $end
$scope module btog $end
$var wire 4 # Bini [3:0] $end
$var wire 4 $ Grayo [3:0] $end
$upscope $end
$scope begin $ivl_for_loop0 $end
$var integer 32 % i [31:0] $end
$upscope $end
$upscope $end
$enddefinitions $end
#0
$dumpvars
b0 %
b0 $
b0 #
b0 "
b0 !
$end
#5
b1 !
b1 $
b1 "
b1 #
b1 %
#10
b11 !
b11 $
b10 "
b10 #
b10 %
#15
b10 !
b10 $
b11 "
b11 #
b11 %
#20
b110 !
b110 $
b100 "
b100 #
b100 %
#25
b111 !
b111 $
b101 "
b101 #
b101 %
#30
b101 !
b101 $
b110 "
b110 #
b110 %
#35
b100 !
b100 $
b111 "
b111 #
b111 %
#40
b1100 !
b1100 $
b1000 "
b1000 #
b1000 %
#45
b1101 !
b1101 $
b1001 "
b1001 #
b1001 %
#50
b1111 !
b1111 $
b1010 "
b1010 #
b1010 %
#55
b1110 !
b1110 $
b1011 "
b1011 #
b1011 %
#60
b1010 !
b1010 $
b1100 "
b1100 #
b1100 %
#65
b1011 !
b1011 $
b1101 "
b1101 #
b1101 %
#70
b1001 !
b1001 $
b1110 "
b1110 #
b1110 %
#75
b1000 !
b1000 $
b1111 "
b1111 #
b1111 %
#80
b10000 %
