Day11_Parallel_to_serial/design.sv
// Code your design here
// Parallel to serial with valid and empty

module day11 (
  input     wire      clk,
  input     wire      reset,

  output    reg      empty_o,
  input     wire[3:0] parallel_i,
  
  output    reg      serial_o,
  output    reg      valid_o
);

  // Shift register for the conversion
   reg[3:0] shift_ff;
   reg[3:0] nxt_shift;

  always @(posedge clk or posedge reset)
    if (reset)
      shift_ff <= 4'h0;
    else
      shift_ff <= nxt_shift;

  // Take the parallel input when empty
  // Otherwise give the data out serially
  assign nxt_shift = empty_o ? parallel_i :
                               {1'b0, shift_ff[3:1]};

  assign serial_o = shift_ff[0];

  // Maintain a counter to drive valid and empty
  reg [2:0] count_ff;
  reg [2:0] nxt_count;

  always @(posedge clk or posedge reset)
    if (reset)
      count_ff <= 3'h0;
    else
      count_ff <= nxt_count;

  // Count goes to zero when it reaches 4 (as all data given out)
  assign nxt_count = (count_ff == 3'h4) ? 3'h0 :
                                          count_ff + 3'h1;

  // Valid when count greater than 0
  assign valid_o = |count_ff;

  // Empty when count_ff == 0
  assign empty_o = (count_ff == 3'h0);

endmodule

Day11_Parallel_to_serial/testbench.sv
// Code your testbench here
// or browse Examples
module day11_tb ();

  reg      clk;
  reg      reset;

  wire      empty_o;
  reg[3:0] parallel_i;
  wire      serial_o;
  wire      valid_o;

  day11 DAY11 (.*);

  // Clock
  always begin
    clk = 1'b1;
    #5;
    clk = 1'b0;
    #5;
  end

  // Stimulus
  initial 
    begin
    reset <= 1'b1;
    parallel_i <= 4'h0;
    @(negedge clk);
    reset <= 1'b0;
    @(posedge clk);
    for (int i=0; i<32; i=i+1)
      begin
      parallel_i <= $urandom_range(0, 4'hF);
      @(posedge clk);
      end
    $finish();
  end

  // VCD
  initial begin
    $dumpfile("day11.vcd");
    $dumpvars(0, day11_tb);
  end

endmodule

Day11_Parallel_to_serial/day11.vcd
$date
	Thu Nov 17 22:12:28 2022
$end
$version
	Icarus Verilog
$end
$timescale
	1s
$end
$scope module day11_tb $end
$var wire 1 ! valid_o $end
$var wire 1 " serial_o $end
$var wire 1 # empty_o $end
$var reg 1 $ clk $end
$var reg 4 % parallel_i [3:0] $end
$var reg 1 & reset $end
$scope module DAY11 $end
$var wire 1 $ clk $end
$var wire 4 ' parallel_i [3:0] $end
$var wire 1 & reset $end
$var wire 1 ! valid_o $end
$var wire 1 " serial_o $end
$var wire 4 ( nxt_shift [3:0] $end
$var wire 3 ) nxt_count [2:0] $end
$var wire 1 # empty_o $end
$var reg 3 * count_ff [2:0] $end
$var reg 4 + shift_ff [3:0] $end
$upscope $end
$scope begin $ivl_for_loop0 $end
$var integer 32 , i [31:0] $end
$upscope $end
$upscope $end
$enddefinitions $end
#0
$dumpvars
b0 ,
b0 +
b0 *
b1 )
b0 (
b0 '
1&
b0 %
1$
1#
0"
0!
$end
#5
0&
0$
#10
b10 )
1!
0#
b1 *
b1001 %
b1001 '
1$
#15
0$
#20
b11 )
b10 *
b100 %
b100 '
b1 ,
1$
#25
0$
#30
b100 )
b11 *
b0 %
b0 '
b10 ,
1$
#35
0$
#40
b0 )
b100 *
b11 %
b11 '
b11 ,
1$
#45
0$
#50
b1 )
b1000 (
0!
1#
b0 *
b1000 %
b1000 '
b100 ,
1$
#55
0$
#60
b10 )
b100 (
1!
0#
b1 *
b1000 +
b1100 %
b1100 '
b101 ,
1$
#65
0$
#70
b10 (
b11 )
b100 +
b10 *
b11 %
b11 '
b110 ,
1$
#75
0$
#80
b1 (
b100 )
b11 *
b10 +
b0 %
b0 '
b111 ,
1$
#85
0$
#90
b0 (
1"
b0 )
b1 +
b100 *
b1000 %
b1000 '
b1000 ,
1$
#95
0$
#100
b1 )
b1000 (
0"
0!
1#
b0 *
b0 +
b1001 ,
1$
#105
0$
#110
b10 )
b100 (
b1000 +
1!
0#
b1 *
b1011 %
b1011 '
b1010 ,
1$
#115
0$
#120
b10 (
b11 )
b10 *
b100 +
b1001 %
b1001 '
b1011 ,
1$
#125
0$
#130
b1 (
b100 )
b10 +
b11 *
b1111 %
b1111 '
b1100 ,
1$
#135
0$
#140
b0 (
b0 )
1"
b100 *
b1 +
b1100 %
b1100 '
b1101 ,
1$
#145
0$
#150
0"
b1 )
b1111 (
b0 +
0!
1#
b0 *
b1111 %
b1111 '
b1110 ,
1$
#155
0$
#160
b10 )
1"
b111 (
1!
0#
b1 *
b1111 +
b110 %
b110 '
b1111 ,
1$
#165
0$
#170
b11 (
b11 )
b111 +
b10 *
b10000 ,
1$
#175
0$
#180
b1 (
b100 )
b11 *
b11 +
b101 %
b101 '
b10001 ,
1$
#185
0$
#190
b0 (
b0 )
b1 +
b100 *
b1111 %
b1111 '
b10010 ,
1$
#195
0$
#200
b1 )
b11 (
0"
0!
1#
b0 *
b0 +
b11 %
b11 '
b10011 ,
1$
#205
0$
#210
1"
b10 )
b1 (
b11 +
1!
0#
b1 *
b0 %
b0 '
b10100 ,
1$
#215
0$
#220
b0 (
b11 )
b10 *
b1 +
b1100 %
b1100 '
b10101 ,
1$
#225
0$
#230
0"
b100 )
b0 +
b11 *
b1111 %
b1111 '
b10110 ,
1$
#235
0$
#240
b0 )
b100 *
b110 %
b110 '
b10111 ,
1$
#245
0$
#250
b1 )
b111 (
0!
1#
b0 *
b111 %
b111 '
b11000 ,
1$
#255
0$
#260
b10 )
1"
b11 (
1!
0#
b1 *
b111 +
b110 %
b110 '
b11001 ,
1$
#265
0$
#270
b1 (
b11 )
b11 +
b10 *
b1010 %
b1010 '
b11010 ,
1$
#275
0$
#280
b0 (
b100 )
b11 *
b1 +
b101 %
b101 '
b11011 ,
1$
#285
0$
#290
0"
b0 )
b0 +
b100 *
b1 %
b1 '
b11100 ,
1$
#295
0$
#300
b1 )
b11 (
0!
1#
b0 *
b11 %
b11 '
b11101 ,
1$
#305
0$
#310
1"
b10 )
b1 (
b11 +
1!
0#
b1 *
b11110 ,
1$
#315
0$
#320
b0 (
b11 )
b10 *
b1 +
b1000 %
b1000 '
b11111 ,
1$
#325
0$
#330
0"
b100 )
b0 +
b11 *
b100000 ,
1$
